inputless_ingestion/__init__.py
inputless_ingestion/ai_extractor.py
inputless_ingestion/exceptions.py
inputless_ingestion/extractors/__init__.py
inputless_ingestion/extractors/docx_extractor.py
inputless_ingestion/extractors/image_extractor.py
inputless_ingestion/extractors/pdf_extractor.py
inputless_ingestion/extractors/text_extractor.py
inputless_ingestion/file_processor.py
inputless_ingestion/graph_integration.py
inputless_ingestion/models.py
inputless_ingestion/nlp_processor.py
inputless_ingestion/ocr_engine.py
inputless_ingestion-1.0.2.dist-info/METADATA
inputless_ingestion-1.0.2.dist-info/WHEEL
inputless_ingestion-1.0.2.dist-info/RECORD
