Metadata-Version: 2.4
Name: inputless-ingestion
Version: 1.0.2
Summary: Document processing and knowledge extraction for Inputless Analytics SDK
Author: Inputless Team
Author-email: team@inputless.io
Requires-Python: >=3.11,<3.14
Classifier: Programming Language :: Python :: 3
Classifier: Programming Language :: Python :: 3.11
Classifier: Programming Language :: Python :: 3.12
Classifier: Programming Language :: Python :: 3.13
Requires-Dist: Pillow (>=10.0.0,<11.0.0)
Requires-Dist: PyPDF2 (>=3.0.0,<4.0.0)
Requires-Dist: aiofiles (>=23.2.1,<24.0.0)
Requires-Dist: anthropic (>=0.30.0,<0.31.0)
Requires-Dist: chardet (>=5.2.0,<6.0.0)
Requires-Dist: langchain (>=0.3.0,<0.4.0)
Requires-Dist: neo4j (>=5.15.0,<6.0.0)
Requires-Dist: nltk (>=3.8.0,<4.0.0)
Requires-Dist: openai (>=1.12.0,<2.0.0)
Requires-Dist: opencv-python (>=4.8.0,<5.0.0)
Requires-Dist: openpyxl (>=3.1.0,<4.0.0)
Requires-Dist: pandas (>=2.1.0,<3.0.0)
Requires-Dist: pdfplumber (>=0.10.0,<0.11.0)
Requires-Dist: pytesseract (>=0.3.10,<0.4.0)
Requires-Dist: python-docx (>=1.1.0,<2.0.0)
Requires-Dist: python-pptx (>=0.6.23,<0.7.0)
Requires-Dist: scikit-learn (>=1.3.0,<2.0.0)
Requires-Dist: spacy (>=3.7.0,<4.0.0)
Requires-Dist: textblob (>=0.17.1,<0.18.0)
